phonescrape/__init__.py
phonescrape-0.0.1.dist-info/LICENSE
phonescrape-0.0.1.dist-info/METADATA
phonescrape-0.0.1.dist-info/WHEEL
phonescrape-0.0.1.dist-info/top_level.txt
phonescrape-0.0.1.dist-info/RECORD
