Metadata-Version: 2.1
Name: phonescrape
Version: 0.0.1
Summary: Downloads and parses information from Cisco IP Phones
Home-page: https://github.com/levensailor/phonescrape
Author: Jeff Levensailor
Author-email: jeff@levensailor.com
License: UNKNOWN
Platform: UNKNOWN
Classifier: Programming Language :: Python :: 3
Classifier: License :: OSI Approved :: MIT License
Classifier: Operating System :: OS Independent
